roulier/__init__.py
roulier/api.py
roulier/carrier_action.py
roulier/codec.py
roulier/exception.py
roulier/roulier.py
roulier/transport.py
roulier/ws_tools.py
roulier/carriers/__init__.py
roulier/carriers/chronopost_fr/__init__.py
roulier/carriers/chronopost_fr/api.py
roulier/carriers/chronopost_fr/carrier_action.py
roulier/carriers/chronopost_fr/decoder.py
roulier/carriers/chronopost_fr/encoder.py
roulier/carriers/chronopost_fr/transport.py
roulier/carriers/chronopost_fr/templates/chronopost_get_label.xml
roulier/carriers/chronopost_fr/templates/chronopost_soap.xml
roulier/carriers/dpd_fr_soap/__init__.py
roulier/carriers/dpd_fr_soap/api.py
roulier/carriers/dpd_fr_soap/carrier_action.py
roulier/carriers/dpd_fr_soap/decoder.py
roulier/carriers/dpd_fr_soap/encoder.py
roulier/carriers/dpd_fr_soap/transport.py
roulier/carriers/dpd_fr_soap/templates/dpd_address.xml
roulier/carriers/dpd_fr_soap/templates/dpd_addressInfo.xml
roulier/carriers/dpd_fr_soap/templates/dpd_createShipmentWithLabels.xml
roulier/carriers/dpd_fr_soap/templates/dpd_header.xml
roulier/carriers/dpd_fr_soap/templates/dpd_soap.xml
roulier/carriers/dpd_fr_soap/tests/__init__.py
roulier/carriers/dpd_fr_soap/tests/credential_demo.py
roulier/carriers/dpd_fr_soap/tests/data.py
roulier/carriers/dpd_fr_soap/tests/test_dpd.py
roulier/carriers/geodis_fr/__init__.py
roulier/carriers/geodis_fr/geodis_rest_api.py
roulier/carriers/geodis_fr/geodis_soap_transport.py
roulier/carriers/geodis_fr/geodis_transport_rest.py
roulier/carriers/geodis_fr/edi/__init__.py
roulier/carriers/geodis_fr/edi/api.py
roulier/carriers/geodis_fr/edi/carrier_action.py
roulier/carriers/geodis_fr/edi/encoder.py
roulier/carriers/geodis_fr/edi/transport.py
roulier/carriers/geodis_fr/get_label/__init__.py
roulier/carriers/geodis_fr/get_label/api.py
roulier/carriers/geodis_fr/get_label/carrier_action.py
roulier/carriers/geodis_fr/get_label/decoder.py
roulier/carriers/geodis_fr/get_label/encoder.py
roulier-1.1.1.dist-info/LICENSE
roulier-1.1.1.dist-info/METADATA
roulier-1.1.1.dist-info/WHEEL
roulier-1.1.1.dist-info/top_level.txt
roulier-1.1.1.dist-info/RECORD
