Metadata-Version: 2.1
Name: roulier
Version: 1.1.1
Summary: Label parcels without pain
Home-page: https://github.com/akretion/roulier
Download-URL: https://github.com/akretion/roulier/archive/1.1.1.zip
Author: Hparfr <https://github.com/hparfr>
Author-email: roulier@hpar.fr
Keywords: carrier,logistics,delivery
Classifier: Development Status :: 4 - Beta
Classifier: Intended Audience :: Developers
Classifier: Topic :: Software Development :: Build Tools
Classifier: License :: OSI Approved :: GNU Affero General Public License v3
Classifier: Programming Language :: Python :: 3.6
License-File: LICENSE
Requires-Dist: lxml
Requires-Dist: Jinja2
Requires-Dist: requests
Requires-Dist: cerberus
Requires-Dist: zplgrf
Requires-Dist: unidecode
Requires-Dist: pycountry
